<?xml version="1.0" encoding="UTF-8"?>
<!DOCTYPE struts PUBLIC
		"-//Apache Software Foundation//DTD Struts Configuration 2.0//EN"
		"http://struts.apache.org/dtds/struts-2.0.dtd">
<struts>
	<constant name="struts.devMode" value="true"/>

	<package name="gallery-struts2" extends="struts-default">
		<global-results>
			<result name="redirect" type="redirectAction">
				${action}
			</result>
		</global-results>

		<action name="Gallery" class="net.feminaexlux.gallery.struts2.controller.Gallery">
			<result>
				/view/gallery/gallery.jsp
			</result>
		</action>

		<action name="Login" class="net.feminaexlux.gallery.struts2.controller.Login">
			<result>
				/view/login/login.jsp
			</result>
		</action>

		<action name="Administration" class="net.feminaexlux.gallery.struts2.controller.Administration">
			<result>
				/view/administration/administration.jsp
			</result>
		</action>

		<action name="ImageLoader" class="net.feminaexlux.gallery.struts2.controller.ImageLoader">
			<result>
				/view/gallery/image.jsp
			</result>
		</action>
	</package>
</struts>